english_ipa/__init__.py
english_ipa/cambridge.py
english_ipa/cambridge_async.py
english_ipa/model/IPA.py
english_ipa/model/region.py
english_ipa/model/word.py
english_ipa/utils.py
english_ipa-1.0.0.dist-info/METADATA
english_ipa-1.0.0.dist-info/WHEEL
english_ipa-1.0.0.dist-info/RECORD
